temdb/models/__init__.py
temdb/models/acquisition.py
temdb/models/block.py
temdb/models/cutting_session.py
temdb/models/enums.py
temdb/models/error.py
temdb/models/quality_control.py
temdb/models/roi.py
temdb/models/section.py
temdb/models/specimen.py
temdb/models/substrate.py
temdb/models/task.py
temdb/models/tile.py
temdb_models-2.0.0.dist-info/METADATA
temdb_models-2.0.0.dist-info/WHEEL
temdb_models-2.0.0.dist-info/RECORD
