Metadata-Version: 2.4
Name: temdb-models
Version: 2.0.0
Summary: Shared Pydantic models for TEMdb
Requires-Python: >=3.10
Requires-Dist: pydantic>=2.0
